pyPayNowSg/EMVCoHeaders.py
pyPayNowSg/EMVCoSerializer.py
pyPayNowSg/PayNowConfigFactory.py
pyPayNowSg/PayNowHeaders.py
pyPayNowSg/PayNowSerializer.py
pyPayNowSg/__init__.py
pyPayNowSg-0.8.1.dist-info/LICENSE.txt
pyPayNowSg-0.8.1.dist-info/METADATA
pyPayNowSg-0.8.1.dist-info/WHEEL
pyPayNowSg-0.8.1.dist-info/top_level.txt
pyPayNowSg-0.8.1.dist-info/RECORD
