Metadata-Version: 2.1
Name: pyPayNowSg
Version: 0.8.1
Summary: A python package to generate Singapore PayNow QR code payloads
Home-page: https://github.com/daffodilistic/pyPayNowSg
Author: Soh Thiam Hing
Author-email: daffodilistic@gmail.com
License: UNKNOWN
Project-URL: Bug Reports, https://github.com/daffodilistic/pyPayNowSg/issues
Project-URL: Source, https://github.com/daffodilistic/pyPayNowSg
Keywords: sample setuptools development
Platform: UNKNOWN
Classifier: Development Status :: 4 - Beta
Classifier: Intended Audience :: Developers
Classifier: Topic :: Software Development :: Libraries
Classifier: License :: OSI Approved :: Open Software License 3.0 (OSL-3.0)
Classifier: Programming Language :: Python :: 2.7
Classifier: Programming Language :: Python :: 3.5
Classifier: Programming Language :: Python :: 3.6
Classifier: Programming Language :: Python :: 3.7
Classifier: Programming Language :: Python :: 3.8
Classifier: Programming Language :: Python :: 3.9
Classifier: Operating System :: OS Independent
Requires-Python: >=2.7, <4
License-File: LICENSE.txt
Requires-Dist: crcmod
Requires-Dist: Pillow
Provides-Extra: dev
Requires-Dist: check-manifest ; extra == 'dev'
